pyaudioconvert/__init__.py
pyaudioconvert-0.0.5.dist-info/LICENSE
pyaudioconvert-0.0.5.dist-info/METADATA
pyaudioconvert-0.0.5.dist-info/WHEEL
pyaudioconvert-0.0.5.dist-info/top_level.txt
pyaudioconvert-0.0.5.dist-info/RECORD
