Metadata-Version: 2.1
Name: pyaudioconvert
Version: 0.0.5
Summary: A small package to convert audio files
Home-page: https://github.com/robmsmt/pyaudioconvert
Author: Rob Smith
Author-email: robmsmt@gmail.com
License: UNKNOWN
Platform: UNKNOWN
Classifier: Programming Language :: Python :: 3
Classifier: License :: OSI Approved :: MIT License
Classifier: Operating System :: OS Independent
